dienen/__init__.py
dienen/callbacks/__init__.py
dienen/callbacks/save_checkpoints.py
dienen/callbacks/schedulers.py
dienen/callbacks/wandb_log.py
dienen/config_processors/__init__.py
dienen/config_processors/architecture_config.py
dienen/config_processors/unfolders.py
dienen/config_processors/utils.py
dienen/core/__init__.py
dienen/core/architecture.py
dienen/core/file.py
dienen/core/layer.py
dienen/core/model.py
dienen/core/node.py
dienen/core/training.py
dienen/layers/__init__.py
dienen/layers/activations.py
dienen/layers/algebra.py
dienen/layers/basic_layers.py
dienen/layers/convolutions.py
dienen/layers/gradient.py
dienen/layers/initialization.py
dienen/layers/losses.py
dienen/layers/signal_layers.py
dienen/layers/transformers.py
dienen/layers/vq.py
dienen/utils/__init__.py
dienen/utils/modiuls.py
dienen-0.0.2.dist-info/LICENSE
dienen-0.0.2.dist-info/METADATA
dienen-0.0.2.dist-info/WHEEL
dienen-0.0.2.dist-info/top_level.txt
dienen-0.0.2.dist-info/RECORD
